roamresearch_client_py/__init__.py
roamresearch_client_py/__main__.py
roamresearch_client_py/cli.py
roamresearch_client_py/client.py
roamresearch_client_py/config.py
roamresearch_client_py/diff.py
roamresearch_client_py/formatter.py
roamresearch_client_py/gfm_to_roam.py
roamresearch_client_py/server.py
roamresearch_client_py/structs.py
roamresearch_client_py/verify.py
roamresearch_client_py-0.4.1.dist-info/METADATA
roamresearch_client_py-0.4.1.dist-info/WHEEL
roamresearch_client_py-0.4.1.dist-info/entry_points.txt
roamresearch_client_py-0.4.1.dist-info/licenses/LICENSE
roamresearch_client_py-0.4.1.dist-info/RECORD
