Metadata-Version: 2.4
Name: roamresearch-client-py
Version: 0.4.1
Summary: Roam Research Python client with built-in CLI and MCP server support.
Project-URL: Homepage, https://github.com/Leechael/roamresearch-client-py
Project-URL: Repository, https://github.com/Leechael/roamresearch-client-py
Project-URL: Issues, https://github.com/Leechael/roamresearch-client-py/issues
Author-email: Leechael Yim <yanleech@gmail.com>
License: MIT
License-File: LICENSE
Keywords: cli,knowledge-graph,mcp,note-taking,roam,roamresearch
Classifier: Development Status :: 4 - Beta
Classifier: Environment :: Console
Classifier: Intended Audience :: Developers
Classifier: License :: OSI Approved :: MIT License
Classifier: Operating System :: OS Independent
Classifier: Programming Language :: Python :: 3
Classifier: Programming Language :: Python :: 3.10
Classifier: Programming Language :: Python :: 3.11
Classifier: Programming Language :: Python :: 3.12
Classifier: Topic :: Software Development :: Libraries :: Python Modules
Requires-Python: >=3.10
Requires-Dist: fastapi>=0.115.12
Requires-Dist: httpx[socks]>=0.28.1
Requires-Dist: mcp[cli]>=1.8.0
Requires-Dist: mistune>=3.1.3
Requires-Dist: pendulum>=3.1.0
Requires-Dist: python-dotenv>=1.0.1
Requires-Dist: toml>=0.10.2
Requires-Dist: uvicorn>=0.32.0
Provides-Extra: dev
Requires-Dist: ipython>=8.36.0; extra == 'dev'
Requires-Dist: pytest>=8.3.5; extra == 'dev'
